h3_landmarks/__init__.py
h3_landmarks/_modidx.py
h3_landmarks/core.py
h3_landmarks/h3_landmarks.py
h3_landmarks-0.0.1.dist-info/LICENSE
h3_landmarks-0.0.1.dist-info/METADATA
h3_landmarks-0.0.1.dist-info/WHEEL
h3_landmarks-0.0.1.dist-info/entry_points.txt
h3_landmarks-0.0.1.dist-info/top_level.txt
h3_landmarks-0.0.1.dist-info/RECORD
