Metadata-Version: 2.1
Name: h3-landmarks
Version: 0.0.1
Summary: Name Hex IDs with landmarks from OpenStreetMap.
Home-page: https://github.com/bkowshik/h3-landmarks
Author: Bhargav Kowshik
Author-email: bhargav.kowshik@gmail.com
License: Apache Software License 2.0
Keywords: nbdev jupyter notebook python
Platform: UNKNOWN
Classifier: Development Status :: 4 - Beta
Classifier: Intended Audience :: Developers
Classifier: Natural Language :: English
Classifier: Programming Language :: Python :: 3.7
Classifier: Programming Language :: Python :: 3.8
Classifier: Programming Language :: Python :: 3.9
Classifier: Programming Language :: Python :: 3.10
Classifier: License :: OSI Approved :: Apache Software License
Requires-Python: >=3.7
Provides-Extra: dev
